{
"type": "FeatureCollection",
"name": "titikInputlokasi",
"crs": { "type": "name", "properties": { "name": "urn:ogc:def:crs:OGC:1.3:CRS84" } },
"features": [
{ "type": "Feature", "properties": { "wkt_geom": "NULL", "id": 11.0, "nama": "Cek Ability", "deskripsi": "Tes PDF", "latitude": -7.79867, "longitude": 110.36342, "foto": "Soal_Pak_Karen.pdf", "created_at": "2023-03-13T18:21:08.000", "updated_at": "2023-03-13T18:21:08.000", "deleted_at": null }, "geometry": { "type": "Point", "coordinates": [ 110.36342, -7.79867 ] } },
{ "type": "Feature", "properties": { "wkt_geom": "NULL", "id": 10.0, "nama": "Area contoh 1", "deskripsi": "Area contoh 1", "latitude": -7.79753, "longitude": 110.38792, "foto": null, "created_at": "2023-03-13T07:42:18.000", "updated_at": "2023-03-13T07:42:18.000", "deleted_at": null }, "geometry": { "type": "Point", "coordinates": [ 110.38792, -7.79753 ] } },
{ "type": "Feature", "properties": { "wkt_geom": "NULL", "id": 9.0, "nama": "Padang Golf Adisucipto", "deskripsi": "Padang Golf Adisucipto", "latitude": -7.79574, "longitude": 110.43144, "foto": "Padang_Golf_Adisucipto.jpeg", "created_at": "2023-03-13T07:02:46.000", "updated_at": "2023-03-13T07:02:46.000", "deleted_at": null }, "geometry": { "type": "Point", "coordinates": [ 110.43144, -7.79574 ] } },
{ "type": "Feature", "properties": { "wkt_geom": "NULL", "id": 8.0, "nama": "GOR Among Rogo", "deskripsi": "GOR Among Rogo", "latitude": -7.7985, "longitude": 110.3854, "foto": "Gor+Among+Rogo.jpg", "created_at": "2023-03-13T06:59:48.000", "updated_at": "2023-03-13T06:59:48.000", "deleted_at": null }, "geometry": { "type": "Point", "coordinates": [ 110.3854, -7.7985 ] } },
{ "type": "Feature", "properties": { "wkt_geom": "NULL", "id": 7.0, "nama": "Stadion Mandala Krida", "deskripsi": "Stadion Mandala Krida", "latitude": -7.79617, "longitude": 110.38427, "foto": "mandala_krida.jpg", "created_at": "2023-03-13T06:53:13.000", "updated_at": "2023-03-13T06:53:13.000", "deleted_at": null }, "geometry": { "type": "Point", "coordinates": [ 110.38427, -7.79617 ] } },
{ "type": "Feature", "properties": { "wkt_geom": "NULL", "id": 6.0, "nama": "jyyu", "deskripsi": "kjghj", "latitude": -7.80003, "longitude": 110.34839, "foto": null, "created_at": "2023-03-06T08:25:57.000", "updated_at": "2023-03-06T08:25:57.000", "deleted_at": null }, "geometry": { "type": "Point", "coordinates": [ 110.34839, -7.80003 ] } },
{ "type": "Feature", "properties": { "wkt_geom": "NULL", "id": 5.0, "nama": "Lokasilah", "deskripsi": "entah di mana", "latitude": -7.79694, "longitude": 110.36072, "foto": null, "created_at": "2023-03-06T08:15:32.000", "updated_at": "2023-03-06T08:15:32.000", "deleted_at": null }, "geometry": { "type": "Point", "coordinates": [ 110.36072, -7.79694 ] } },
{ "type": "Feature", "properties": { "wkt_geom": "NULL", "id": 4.0, "nama": "jshfl", "deskripsi": "sdgrwgr", "latitude": -7.80059, "longitude": 110.37736, "foto": null, "created_at": "2023-03-06T08:11:46.000", "updated_at": "2023-03-06T08:11:46.000", "deleted_at": null }, "geometry": { "type": "Point", "coordinates": [ 110.37736, -7.80059 ] } },
{ "type": "Feature", "properties": { "wkt_geom": "NULL", "id": 3.0, "nama": "alkid", "deskripsi": "alun-alun kidul", "latitude": -7.81211, "longitude": 110.36342, "foto": null, "created_at": "2023-03-06T08:11:34.000", "updated_at": "2023-03-06T08:11:34.000", "deleted_at": null }, "geometry": { "type": "Point", "coordinates": [ 110.36342, -7.81211 ] } },
{ "type": "Feature", "properties": { "wkt_geom": "NULL", "id": 2.0, "nama": "alkid", "deskripsi": "alun-alun kidul", "latitude": -7.81207, "longitude": 110.36337, "foto": null, "created_at": "2023-03-06T07:31:24.000", "updated_at": "2023-03-06T07:31:24.000", "deleted_at": null }, "geometry": { "type": "Point", "coordinates": [ 110.36337, -7.81207 ] } },
{ "type": "Feature", "properties": { "wkt_geom": "NULL", "id": 1.0, "nama": "alkid", "deskripsi": "alun-alun kidul", "latitude": -7.8042, "longitude": 110.36449, "foto": null, "created_at": null, "updated_at": null, "deleted_at": null }, "geometry": { "type": "Point", "coordinates": [ 110.36449, -7.8042 ] } }
]
}
